<annotations><filename>image_18_36_97653_26_30225_37_75359_23_18017_37_76252_23_16872.jpeg</filename><folder>images</folder><size><width>2135</width><height>2106</height><depth>3</depth></size><object><name>c</name><pose>Unspecified</pose><truncated>0</truncated><difficult>0</difficult><bndbox><xmin>548.0</xmin><ymin>104.0</ymin><xmax>616.0</xmax><ymax>168.0</ymax></bndbox></object><object><name>c</name><pose>Unspecified</pose><truncated>0</truncated><difficult>0</difficult><bndbox><xmin>500.0</xmin><ymin>378.0</ymin><xmax>528.0</xmax><ymax>407.0</ymax></bndbox></object><object><name>c</name><pose>Unspecified</pose><truncated>0</truncated><difficult>0</difficult><bndbox><xmin>497.0</xmin><ymin>463.0</ymin><xmax>532.0</xmax><ymax>525.0</ymax></bndbox></object><object><name>c</name><pose>Unspecified</pose><truncated>0</truncated><difficult>0</difficult><bndbox><xmin>546.0</xmin><ymin>359.0</ymin><xmax>580.0</xmax><ymax>391.0</ymax></bndbox></object><object><name>c</name><pose>Unspecified</pose><truncated>0</truncated><difficult>0</difficult><bndbox><xmin>531.0</xmin><ymin>399.0</ymin><xmax>563.0</xmax><ymax>430.0</ymax></bndbox></object><object><name>c</name><pose>Unspecified</pose><truncated>0</truncated><difficult>0</difficult><bndbox><xmin>462.0</xmin><ymin>464.0</ymin><xmax>527.0</xmax><ymax>527.0</ymax></bndbox></object><object><name>c</name><pose>Unspecified</pose><truncated>0</truncated><difficult>0</difficult><bndbox><xmin>504.0</xmin><ymin>334.0</ymin><xmax>535.0</xmax><ymax>367.0</ymax></bndbox></object><object><name>c</name><pose>Unspecified</pose><truncated>0</truncated><difficult>0</difficult><bndbox><xmin>495.0</xmin><ymin>496.0</ymin><xmax>532.0</xmax><ymax>537.0</ymax></bndbox></object><object><name>c</name><pose>Unspecified</pose><truncated>0</truncated><difficult>0</difficult><bndbox><xmin>1210.0</xmin><ymin>783.0</ymin><xmax>1281.0</xmax><ymax>844.0</ymax></bndbox></object><object><name>c</name><pose>Unspecified</pose><truncated>0</truncated><difficult>0</difficult><bndbox><xmin>1310.0</xmin><ymin>689.0</ymin><xmax>1374.0</xmax><ymax>754.0</ymax></bndbox></object><object><name>c</name><pose>Unspecified</pose><truncated>0</truncated><difficult>0</difficult><bndbox><xmin>1122.0</xmin><ymin>900.0</ymin><xmax>1181.0</xmax><ymax>968.0</ymax></bndbox></object><object><name>c</name><pose>Unspecified</pose><truncated>0</truncated><difficult>0</difficult><bndbox><xmin>1387.0</xmin><ymin>567.0</ymin><xmax>1455.0</xmax><ymax>630.0</ymax></bndbox></object><object><name>c</name><pose>Unspecified</pose><truncated>0</truncated><difficult>0</difficult><bndbox><xmin>1020.0</xmin><ymin>1006.0</ymin><xmax>1081.0</xmax><ymax>1027.0</ymax></bndbox></object><object><name>c</name><pose>Unspecified</pose><truncated>0</truncated><difficult>0</difficult><bndbox><xmin>1016.0</xmin><ymin>1011.0</ymin><xmax>1083.0</xmax><ymax>1075.0</ymax></bndbox></object></annotations>