<annotations><filename>image_18_36_6576_22_3654_38_14879_20_38381_38_15744_20_37198.jpeg</filename><folder>images</folder><size><width>2206</width><height>2050</height><depth>3</depth></size><object><name>c</name><pose>Unspecified</pose><truncated>0</truncated><difficult>0</difficult><bndbox><xmin>1955.0000000000002</xmin><ymin>688.0</ymin><xmax>2107.0</xmax><ymax>850.0</ymax></bndbox></object><object><name>c</name><pose>Unspecified</pose><truncated>0</truncated><difficult>0</difficult><bndbox><xmin>2079.0</xmin><ymin>66.0</ymin><xmax>2191.0</xmax><ymax>285.0</ymax></bndbox></object></annotations>