<annotations><filename>image_18_37_29476_26_76637_36_7749_24_53746_36_78397_24_52632.jpeg</filename><folder>images</folder><size><width>2077</width><height>2111</height><depth>3</depth></size><object><name>c</name><pose>Unspecified</pose><truncated>0</truncated><difficult>0</difficult><bndbox><xmin>1631.0</xmin><ymin>696.0</ymin><xmax>1723.0</xmax><ymax>801.0</ymax></bndbox></object><object><name>c</name><pose>Unspecified</pose><truncated>0</truncated><difficult>0</difficult><bndbox><xmin>1994.0</xmin><ymin>16.0</ymin><xmax>2066.0</xmax><ymax>76.0</ymax></bndbox></object></annotations>