<annotations><filename>image_18_36_56076_22_93727_38_36672_21_10524_38_37543_21_09344.jpeg</filename><folder>images</folder><size><width>2200</width><height>2071</height><depth>3</depth></size><object><name>c</name><pose>Unspecified</pose><truncated>0</truncated><difficult>0</difficult><bndbox><xmin>1530.0</xmin><ymin>670.0</ymin><xmax>1589.0</xmax><ymax>713.0</ymax></bndbox></object><object><name>c</name><pose>Unspecified</pose><truncated>0</truncated><difficult>0</difficult><bndbox><xmin>1868.0</xmin><ymin>814.0</ymin><xmax>1916.0</xmax><ymax>854.0</ymax></bndbox></object><object><name>c</name><pose>Unspecified</pose><truncated>0</truncated><difficult>0</difficult><bndbox><xmin>1532.0</xmin><ymin>831.0</ymin><xmax>1579.0</xmax><ymax>879.0</ymax></bndbox></object><object><name>c</name><pose>Unspecified</pose><truncated>0</truncated><difficult>0</difficult><bndbox><xmin>317.0</xmin><ymin>1121.0</ymin><xmax>408.0</xmax><ymax>1267.0</ymax></bndbox></object><object><name>c</name><pose>Unspecified</pose><truncated>0</truncated><difficult>0</difficult><bndbox><xmin>1231.0</xmin><ymin>950.0</ymin><xmax>1301.0</xmax><ymax>1006.0</ymax></bndbox></object><object><name>c</name><pose>Unspecified</pose><truncated>0</truncated><difficult>0</difficult><bndbox><xmin>236.0</xmin><ymin>1680.0</ymin><xmax>287.0</xmax><ymax>1750.0</ymax></bndbox></object><object><name>c</name><pose>Unspecified</pose><truncated>0</truncated><difficult>0</difficult><bndbox><xmin>215.0</xmin><ymin>1887.0</ymin><xmax>489.0</xmax><ymax>1998.0</ymax></bndbox></object><object><name>c</name><pose>Unspecified</pose><truncated>0</truncated><difficult>0</difficult><bndbox><xmin>1713.0</xmin><ymin>1014.0</ymin><xmax>1747.0</xmax><ymax>1045.0</ymax></bndbox></object><object><name>c</name><pose>Unspecified</pose><truncated>0</truncated><difficult>0</difficult><bndbox><xmin>1757.0</xmin><ymin>1388.0</ymin><xmax>1975.0</xmax><ymax>1501.0</ymax></bndbox></object><object><name>c</name><pose>Unspecified</pose><truncated>0</truncated><difficult>0</difficult><bndbox><xmin>1028.0</xmin><ymin>1628.0</ymin><xmax>1292.0</xmax><ymax>1860.0</ymax></bndbox></object></annotations>